pymongo_vectorsearch_utils/__init__.py
pymongo_vectorsearch_utils/_version.py
pymongo_vectorsearch_utils-0.1.0.dev0.dist-info/METADATA
pymongo_vectorsearch_utils-0.1.0.dev0.dist-info/WHEEL
pymongo_vectorsearch_utils-0.1.0.dev0.dist-info/licenses/LICENSE
pymongo_vectorsearch_utils-0.1.0.dev0.dist-info/RECORD
