Metadata-Version: 2.4
Name: pymongo-vectorsearch-utils
Version: 0.1.0.dev0
Summary: Utility library for working with vector search in MongoDB using PyMongo
Project-URL: Download, https://github.com/mongodb-labs/pymongo-vectorsearch-utils/tags
Project-URL: Homepage, http://pymongo-vectorsearch-utils.readthedocs.org/
Author-email: Noah Stapp <noah.stapp@mongodb.com>
License:                                  Apache License
License-File: LICENSE
Classifier: Intended Audience :: Developers
Classifier: License :: OSI Approved :: BSD License
Classifier: Operating System :: OS Independent
Classifier: Programming Language :: Python :: 3.10
Classifier: Programming Language :: Python :: 3.11
Classifier: Programming Language :: Python :: 3.12
Classifier: Programming Language :: Python :: 3.13
Classifier: Programming Language :: Python :: Implementation :: CPython
Classifier: Programming Language :: Python :: Implementation :: PyPy
Classifier: Topic :: Software Development :: Libraries :: Python Modules
Requires-Python: >=3.10
Requires-Dist: pymongo>=4.12.0
